fununit/TestCase.py
fununit/TestResult.py
fununit/TestSuite.py
fununit/UnitTest.py
fununit/__init__.py
fununit/_utils.py
fununit/run.py
fununit/adapters/__init__.py
fununit/adapters/unittest.py
fununit-2.1.0.dist-info/LICENSE
fununit-2.1.0.dist-info/METADATA
fununit-2.1.0.dist-info/WHEEL
fununit-2.1.0.dist-info/top_level.txt
fununit-2.1.0.dist-info/RECORD
